TreeNote/__init__.py
TreeNote/model.py
TreeNote/planned_model.py
TreeNote/tag_model.py
TreeNote/treenote.py
TreeNote/util.py
TreeNote/resources/SourceSansPro-Regular.otf
TreeNote/resources/__init__.py
TreeNote/resources/example_tree.json
TreeNote/resources/example_tree_de_DE.json
TreeNote/resources/qrc_resources.py
TreeNote/resources/resources.qrc
TreeNote/resources/__pycache__/__init__.cpython-35.pyc
TreeNote/resources/__pycache__/qrc_resources.cpython-34.pyc
TreeNote/resources/__pycache__/qrc_resources.cpython-35.pyc
TreeNote/resources/images/logo.icns
TreeNote/resources/images/logo.ico
TreeNote/resources/images/logo.png
TreeNote/resources/images/screenshot.png
TreeNote/resources/images/bright_skin/branch-closed.png
TreeNote/resources/images/bright_skin/branch-open.png
TreeNote/resources/images/bright_skin/done.png
TreeNote/resources/images/bright_skin/parallel.png
TreeNote/resources/images/bright_skin/paused.png
TreeNote/resources/images/bright_skin/search.png
TreeNote/resources/images/bright_skin/sequential.png
TreeNote/resources/images/bright_skin/todo.png
TreeNote/resources/images/dark_skin/closed.png
TreeNote/resources/images/dark_skin/done.png
TreeNote/resources/images/dark_skin/minus.png
TreeNote/resources/images/dark_skin/not_available_todo.png
TreeNote/resources/images/dark_skin/open.png
TreeNote/resources/images/dark_skin/parallel.png
TreeNote/resources/images/dark_skin/paused.png
TreeNote/resources/images/dark_skin/plus.png
TreeNote/resources/images/dark_skin/search.png
TreeNote/resources/images/dark_skin/sequential.png
TreeNote/resources/images/dark_skin/star.png
TreeNote/resources/images/dark_skin/todo.png
TreeNote/resources/images/dark_skin/toggle_columns.png
TreeNote/resources/images/dark_skin/toggle_sidebars.png
TreeNote/resources/locales/treenote_de_DE.qm
TreeNote/resources/locales/treenote_de_DE.ts
TreeNote-1.7.4.dist-info/DESCRIPTION.rst
TreeNote-1.7.4.dist-info/METADATA
TreeNote-1.7.4.dist-info/RECORD
TreeNote-1.7.4.dist-info/WHEEL
TreeNote-1.7.4.dist-info/entry_points.txt
TreeNote-1.7.4.dist-info/metadata.json
TreeNote-1.7.4.dist-info/top_level.txt
