Metadata-Version: 2.0
Name: TreeNote
Version: 1.7.4
Summary: An intuitive outliner for personal knowledge and task management
Home-page: http://treenote.org
Author: Jan Korte
Author-email: j.korte@me.com
License: GPL3
Platform: UNKNOWN
Classifier: Development Status :: 5 - Production/Stable
Classifier: Environment :: X11 Applications :: Qt
Classifier: License :: OSI Approved :: GNU General Public License v3 (GPLv3)
Classifier: Programming Language :: Python :: 3 :: Only
Classifier: Topic :: Text Editors
Requires-Dist: PyQt5
Requires-Dist: SIP
